my_countries_api_1234567/__init__.py
my_countries_api_1234567/api_helper.py
my_countries_api_1234567/configuration.py
my_countries_api_1234567/decorators.py
my_countries_api_1234567/my_countries_api_1234567_client.py
my_countries_api_1234567/controllers/__init__.py
my_countries_api_1234567/controllers/base_controller.py
my_countries_api_1234567/controllers/countries_controller.py
my_countries_api_1234567/exceptions/__init__.py
my_countries_api_1234567/exceptions/api_exception.py
my_countries_api_1234567/http/__init__.py
my_countries_api_1234567/http/http_call_back.py
my_countries_api_1234567/http/http_client.py
my_countries_api_1234567/http/http_context.py
my_countries_api_1234567/http/http_method_enum.py
my_countries_api_1234567/http/http_request.py
my_countries_api_1234567/http/http_response.py
my_countries_api_1234567/http/requests_client.py
my_countries_api_1234567/models/__init__.py
my_countries_api_1234567/models/country_info.py
my_countries_api_1234567/models/country_response.py
tests/__init__.py
tests/http_response_catcher.py
tests/test_helper.py
tests/controllers/__init__.py
tests/controllers/controller_test_base.py
tests/controllers/test_countries_controller.py
My_CountriesAPI_1234567-1.0.dist-info/LICENSE
My_CountriesAPI_1234567-1.0.dist-info/METADATA
My_CountriesAPI_1234567-1.0.dist-info/WHEEL
My_CountriesAPI_1234567-1.0.dist-info/top_level.txt
My_CountriesAPI_1234567-1.0.dist-info/RECORD
